aloha_mysql/__init__.py
aloha_mysql/mysql.py
aloha_mysql/query_builder.py
tests/__init__.py
tests/test_aloha_mysql.py
aloha_mysql_query_builder-0.1.0.dist-info/LICENSE
aloha_mysql_query_builder-0.1.0.dist-info/METADATA
aloha_mysql_query_builder-0.1.0.dist-info/WHEEL
aloha_mysql_query_builder-0.1.0.dist-info/entry_points.txt
aloha_mysql_query_builder-0.1.0.dist-info/top_level.txt
aloha_mysql_query_builder-0.1.0.dist-info/RECORD
