Metadata-Version: 2.1
Name: aloha-mysql-query-builder
Version: 0.1.0
Summary: A MySQL query builder for Python
Home-page: https://github.com/TheadoreL/aloha-mysql
Author: Theadore Lee
Author-email: admin@theadorelee.com
Classifier: Programming Language :: Python :: 3
Classifier: License :: OSI Approved :: MIT License
Classifier: Operating System :: OS Independent
Requires-Python: >=3.6
License-File: LICENSE
Requires-Dist: mysql-connector-python
Requires-Dist: pytest
